{
	"format_version": "1.8.0",
	"render_controllers": {
		"controller.render.freddy": {
			"geometry": "geometry.default",
			"materials": [
				{
					"*": "material.default"
				}
			],
			"textures": [
				"array.variants[query.variant]"
			],
			"arrays": {
				"textures": {
					"Array.variants": [
						"Texture.default",
						"Texture.blue",
						"Texture.red",
						"texture.purple",
						"texture.orange",
						"Texture.green",
						"Texture.shadow",
						"Texture.var1",
						"Texture.var2",
						"Texture.var3"
					]
				}
			}
		}
	}
}