{
	"format_version": "1.12.0",
	"minecraft:geometry": [
		{
			"description": {
				"identifier": "geometry.stack_papers8",
				"texture_width": 16,
				"texture_height": 16,
				"visible_bounds_width": 3,
				"visible_bounds_height": 2.5,
				"visible_bounds_offset": [
					0,
					0.75,
					0
				]
			},
			"bones": [
				{
					"name": "bb_main3",
					"pivot": [
						0,
						0,
						0
					],
					"cubes": [
						{
							"origin": [
								-4,
								0,
								-5
							],
							"size": [
								9,
								2,
								11
							],
							"pivot": [
								0.5,
								7,
								0.5
							],
							"rotation": [
								0,
								-15,
								0
							],
							"uv": {
								"north": {
									"uv": [
										13.75,
										15
									],
									"uv_size": [
										2.25,
										0.5
									]
								},
								"east": {
									"uv": [
										13.75,
										15
									],
									"uv_size": [
										2.25,
										0.5
									]
								},
								"south": {
									"uv": [
										13.75,
										15
									],
									"uv_size": [
										2.25,
										0.5
									]
								},
								"west": {
									"uv": [
										13.75,
										15
									],
									"uv_size": [
										2.25,
										0.5
									]
								},
								"up": {
									"uv": [
										1.75,
										0
									],
									"uv_size": [
										-1.75,
										2.25
									]
								},
								"down": {
									"uv": [
										3.5,
										8.25
									],
									"uv_size": [
										-1.75,
										-2.25
									]
								}
							}
						}
					]
				},
				{
					"name": "bb_main",
					"pivot": [
						0,
						0,
						0
					],
					"cubes": [
						{
							"origin": [
								-1,
								0,
								-1
							],
							"size": [
								2,
								2,
								2
							],
							"uv": {
								"north": {
									"uv": [
										2.5,
										2.5
									],
									"uv_size": [
										0.5,
										0.5
									]
								},
								"east": {
									"uv": [
										2.5,
										2.5
									],
									"uv_size": [
										0.5,
										0.5
									]
								},
								"south": {
									"uv": [
										2.5,
										2.5
									],
									"uv_size": [
										0.5,
										0.5
									]
								},
								"west": {
									"uv": [
										2.5,
										2.5
									],
									"uv_size": [
										0.5,
										0.5
									]
								},
								"up": {
									"uv": [
										3,
										3
									],
									"uv_size": [
										-0.5,
										-0.5
									]
								},
								"down": {
									"uv": [
										3,
										3
									],
									"uv_size": [
										-0.5,
										-0.5
									]
								}
							}
						}
					]
				},
				{
					"name": "bb_main2",
					"pivot": [
						0,
						2,
						0
					],
					"cubes": [
						{
							"origin": [
								-4,
								2,
								-5
							],
							"size": [
								9,
								2,
								11
							],
							"pivot": [
								0.5,
								9,
								0.5
							],
							"rotation": [
								0,
								-15,
								0
							],
							"uv": {
								"north": {
									"uv": [
										13.75,
										15
									],
									"uv_size": [
										2.25,
										0.5
									]
								},
								"east": {
									"uv": [
										13.75,
										15
									],
									"uv_size": [
										2.25,
										0.5
									]
								},
								"south": {
									"uv": [
										13.75,
										15
									],
									"uv_size": [
										2.25,
										0.5
									]
								},
								"west": {
									"uv": [
										13.75,
										15
									],
									"uv_size": [
										2.25,
										0.5
									]
								},
								"up": {
									"uv": [
										1.75,
										0
									],
									"uv_size": [
										-1.75,
										2.25
									]
								},
								"down": {
									"uv": [
										3.5,
										8.25
									],
									"uv_size": [
										-1.75,
										-2.25
									]
								}
							}
						}
					]
				},
				{
					"name": "bb_main4",
					"pivot": [
						0,
						4,
						0
					],
					"cubes": [
						{
							"origin": [
								-4,
								4,
								-5
							],
							"size": [
								9,
								2,
								11
							],
							"pivot": [
								0.5,
								11,
								0.5
							],
							"rotation": [
								0,
								-15,
								0
							],
							"uv": {
								"north": {
									"uv": [
										13.75,
										15
									],
									"uv_size": [
										2.25,
										0.5
									]
								},
								"east": {
									"uv": [
										13.75,
										15
									],
									"uv_size": [
										2.25,
										0.5
									]
								},
								"south": {
									"uv": [
										13.75,
										15
									],
									"uv_size": [
										2.25,
										0.5
									]
								},
								"west": {
									"uv": [
										13.75,
										15
									],
									"uv_size": [
										2.25,
										0.5
									]
								},
								"up": {
									"uv": [
										1.75,
										0
									],
									"uv_size": [
										-1.75,
										2.25
									]
								},
								"down": {
									"uv": [
										3.5,
										8.25
									],
									"uv_size": [
										-1.75,
										-2.25
									]
								}
							}
						}
					]
				},
				{
					"name": "bb_main5",
					"pivot": [
						0,
						6,
						0
					],
					"cubes": [
						{
							"origin": [
								-4,
								6,
								-5
							],
							"size": [
								9,
								2,
								11
							],
							"pivot": [
								0.5,
								13,
								0.5
							],
							"rotation": [
								0,
								-15,
								0
							],
							"uv": {
								"north": {
									"uv": [
										13.75,
										15
									],
									"uv_size": [
										2.25,
										0.5
									]
								},
								"east": {
									"uv": [
										13.75,
										15
									],
									"uv_size": [
										2.25,
										0.5
									]
								},
								"south": {
									"uv": [
										13.75,
										15
									],
									"uv_size": [
										2.25,
										0.5
									]
								},
								"west": {
									"uv": [
										13.75,
										15
									],
									"uv_size": [
										2.25,
										0.5
									]
								},
								"up": {
									"uv": [
										1.75,
										0
									],
									"uv_size": [
										-1.75,
										2.25
									]
								},
								"down": {
									"uv": [
										3.5,
										8.25
									],
									"uv_size": [
										-1.75,
										-2.25
									]
								}
							}
						}
					]
				},
				{
					"name": "bb_main6",
					"pivot": [
						0,
						8,
						0
					],
					"cubes": [
						{
							"origin": [
								-4,
								8,
								-5
							],
							"size": [
								9,
								2,
								11
							],
							"pivot": [
								0.5,
								15,
								0.5
							],
							"rotation": [
								0,
								-15,
								0
							],
							"uv": {
								"north": {
									"uv": [
										13.75,
										15
									],
									"uv_size": [
										2.25,
										0.5
									]
								},
								"east": {
									"uv": [
										13.75,
										15
									],
									"uv_size": [
										2.25,
										0.5
									]
								},
								"south": {
									"uv": [
										13.75,
										15
									],
									"uv_size": [
										2.25,
										0.5
									]
								},
								"west": {
									"uv": [
										13.75,
										15
									],
									"uv_size": [
										2.25,
										0.5
									]
								},
								"up": {
									"uv": [
										1.75,
										0
									],
									"uv_size": [
										-1.75,
										2.25
									]
								},
								"down": {
									"uv": [
										3.5,
										8.25
									],
									"uv_size": [
										-1.75,
										-2.25
									]
								}
							}
						}
					]
				},
				{
					"name": "bb_main7",
					"pivot": [
						0,
						10,
						0
					],
					"cubes": [
						{
							"origin": [
								-4,
								10,
								-5
							],
							"size": [
								9,
								2,
								11
							],
							"pivot": [
								0.5,
								17,
								0.5
							],
							"rotation": [
								0,
								-15,
								0
							],
							"uv": {
								"north": {
									"uv": [
										13.75,
										15
									],
									"uv_size": [
										2.25,
										0.5
									]
								},
								"east": {
									"uv": [
										13.75,
										15
									],
									"uv_size": [
										2.25,
										0.5
									]
								},
								"south": {
									"uv": [
										13.75,
										15
									],
									"uv_size": [
										2.25,
										0.5
									]
								},
								"west": {
									"uv": [
										13.75,
										15
									],
									"uv_size": [
										2.25,
										0.5
									]
								},
								"up": {
									"uv": [
										1.75,
										0
									],
									"uv_size": [
										-1.75,
										2.25
									]
								},
								"down": {
									"uv": [
										3.5,
										8.25
									],
									"uv_size": [
										-1.75,
										-2.25
									]
								}
							}
						}
					]
				},
				{
					"name": "bb_main8",
					"pivot": [
						0,
						12,
						0
					],
					"cubes": [
						{
							"origin": [
								-4,
								12,
								-5
							],
							"size": [
								9,
								2,
								11
							],
							"pivot": [
								0.5,
								19,
								0.5
							],
							"rotation": [
								0,
								-15,
								0
							],
							"uv": {
								"north": {
									"uv": [
										13.75,
										15
									],
									"uv_size": [
										2.25,
										0.5
									]
								},
								"east": {
									"uv": [
										13.75,
										15
									],
									"uv_size": [
										2.25,
										0.5
									]
								},
								"south": {
									"uv": [
										13.75,
										15
									],
									"uv_size": [
										2.25,
										0.5
									]
								},
								"west": {
									"uv": [
										13.75,
										15
									],
									"uv_size": [
										2.25,
										0.5
									]
								},
								"up": {
									"uv": [
										1.75,
										0
									],
									"uv_size": [
										-1.75,
										2.25
									]
								},
								"down": {
									"uv": [
										3.5,
										8.25
									],
									"uv_size": [
										-1.75,
										-2.25
									]
								}
							}
						}
					]
				}
			]
		}
	]
}