{
	"format_version": "1.12.0",
	"minecraft:geometry": [
		{
			"description": {
				"identifier": "geometry.fb_fixed_foxy_suit",
				"texture_width": 16,
				"texture_height": 16,
				"visible_bounds_width": 3,
				"visible_bounds_height": 4.5,
				"visible_bounds_offset": [
					0,
					1.75,
					0
				]
			},
			"bones": [
				{
					"name": "Body",
					"pivot": [
						0,
						24,
						0
					],
					"cubes": [
						{
							"origin": [
								-3.348,
								15.12,
								-2.228
							],
							"size": [
								6.748,
								4.8,
								4.416
							],
							"uv": {
								"north": {
									"uv": [
										8.25,
										0.625
									],
									"uv_size": [
										1.125,
										-0.625
									]
								},
								"east": {
									"uv": [
										2.875,
										2.5
									],
									"uv_size": [
										0.625,
										0.625
									]
								},
								"south": {
									"uv": [
										8.25,
										1.875
									],
									"uv_size": [
										1.125,
										0.625
									]
								},
								"west": {
									"uv": [
										2.875,
										3.75
									],
									"uv_size": [
										0.625,
										0.625
									]
								},
								"up": {
									"uv": [
										2.875,
										1.25
									],
									"uv_size": [
										1.375,
										0.625
									]
								},
								"down": {
									"uv": [
										1.5,
										3.5
									],
									"uv_size": [
										1.375,
										-0.625
									]
								}
							},
							"inflate": 0
						},
						{
							"origin": [
								-4.384,
								19.42,
								-2.708
							],
							"size": [
								8.772,
								5.8,
								5.376
							],
							"uv": {
								"north": {
									"uv": [
										0,
										0.5
									],
									"uv_size": [
										1.375,
										0.625
									]
								},
								"east": {
									"uv": [
										2.875,
										1.875
									],
									"uv_size": [
										0.625,
										1.25
									]
								},
								"south": {
									"uv": [
										0,
										1.25
									],
									"uv_size": [
										1.375,
										0.625
									]
								},
								"west": {
									"uv": [
										2.875,
										3.125
									],
									"uv_size": [
										0.625,
										1.25
									]
								},
								"up": {
									"uv": [
										2.875,
										1.25
									],
									"uv_size": [
										1.375,
										0.625
									]
								},
								"down": {
									"uv": [
										1.5,
										3.5
									],
									"uv_size": [
										1.375,
										-0.625
									]
								}
							},
							"inflate": 0
						},
						{
							"origin": [
								-4.07,
								20.76,
								-0.704
							],
							"size": [
								8.184,
								3.52,
								2.288
							],
							"uv": {
								"north": {
									"uv": [
										4.25,
										1.25
									],
									"uv_size": [
										1.125,
										0.625
									]
								},
								"east": {
									"uv": [
										4.25,
										1.25
									],
									"uv_size": [
										0.375,
										0.625
									]
								},
								"south": {
									"uv": [
										4.25,
										1.25
									],
									"uv_size": [
										1.125,
										0.625
									]
								},
								"west": {
									"uv": [
										5,
										1.25
									],
									"uv_size": [
										0.375,
										0.625
									]
								},
								"up": {
									"uv": [
										4.25,
										1.375
									],
									"uv_size": [
										1.125,
										0.375
									]
								},
								"down": {
									"uv": [
										4.25,
										1.75
									],
									"uv_size": [
										1.125,
										-0.375
									]
								}
							},
							"inflate": 0
						},
						{
							"origin": [
								-2.97,
								13.48,
								-0.704
							],
							"size": [
								5.984,
								5.06,
								2.288
							],
							"uv": {
								"north": {
									"uv": [
										4.25,
										1.25
									],
									"uv_size": [
										1.125,
										0.625
									]
								},
								"east": {
									"uv": [
										4.25,
										1.25
									],
									"uv_size": [
										0.375,
										0.625
									]
								},
								"south": {
									"uv": [
										4.25,
										1.25
									],
									"uv_size": [
										1.125,
										0.625
									]
								},
								"west": {
									"uv": [
										5,
										1.25
									],
									"uv_size": [
										0.375,
										0.625
									]
								},
								"up": {
									"uv": [
										4.25,
										1.375
									],
									"uv_size": [
										1.125,
										0.375
									]
								},
								"down": {
									"uv": [
										4.25,
										1.75
									],
									"uv_size": [
										1.125,
										-0.375
									]
								}
							},
							"inflate": 0
						},
						{
							"origin": [
								-1.166,
								24.28,
								-0.704
							],
							"size": [
								2.288,
								1.76,
								2.288
							],
							"uv": {
								"north": {
									"uv": [
										5,
										1
									],
									"uv_size": [
										0.375,
										0.25
									]
								},
								"east": {
									"uv": [
										1.875,
										7.5
									],
									"uv_size": [
										0.375,
										0.25
									]
								},
								"south": {
									"uv": [
										7.625,
										2.875
									],
									"uv_size": [
										0.375,
										0.25
									]
								},
								"west": {
									"uv": [
										7.625,
										3.125
									],
									"uv_size": [
										0.375,
										0.25
									]
								},
								"up": {
									"uv": [
										7.125,
										4.75
									],
									"uv_size": [
										0.375,
										0.375
									]
								},
								"down": {
									"uv": [
										5.375,
										7.5
									],
									"uv_size": [
										0.375,
										-0.375
									]
								}
							},
							"inflate": 0
						},
						{
							"origin": [
								-3.84,
								11.6,
								-1.6
							],
							"size": [
								7.84,
								3.2,
								4
							],
							"uv": {
								"north": {
									"uv": [
										3.5,
										2.75
									],
									"uv_size": [
										1.5,
										0.5
									]
								},
								"east": {
									"uv": [
										4.375,
										0.75
									],
									"uv_size": [
										0.625,
										0.5
									]
								},
								"south": {
									"uv": [
										3.5,
										3.25
									],
									"uv_size": [
										1.5,
										0.5
									]
								},
								"west": {
									"uv": [
										6.25,
										1.75
									],
									"uv_size": [
										0.625,
										0.5
									]
								},
								"up": {
									"uv": [
										2.875,
										0
									],
									"uv_size": [
										1.5,
										0.625
									]
								},
								"down": {
									"uv": [
										2.875,
										1.25
									],
									"uv_size": [
										1.5,
										-0.625
									]
								}
							},
							"inflate": 0
						}
					]
				},
				{
					"name": "RightArm",
					"pivot": [
						-5,
						22,
						0
					]
				},
				{
					"name": "bone23",
					"pivot": [
						-4.99838,
						24.8434,
						-0.00412
					],
					"cubes": [
						{
							"origin": [
								-6.64,
								20.528,
								-1.204
							],
							"size": [
								2.288,
								4.4,
								2.288
							],
							"uv": {
								"north": {
									"uv": [
										5.375,
										1
									],
									"uv_size": [
										0.375,
										0.5
									]
								},
								"east": {
									"uv": [
										5.375,
										1
									],
									"uv_size": [
										0.375,
										0.5
									]
								},
								"south": {
									"uv": [
										5.375,
										1
									],
									"uv_size": [
										0.375,
										0.5
									]
								},
								"west": {
									"uv": [
										5.375,
										1
									],
									"uv_size": [
										0.375,
										0.5
									]
								},
								"up": {
									"uv": [
										5.75,
										1.5
									],
									"uv_size": [
										-0.375,
										-0.5
									]
								},
								"down": {
									"uv": [
										5.75,
										1.5
									],
									"uv_size": [
										-0.375,
										-0.5
									]
								}
							},
							"inflate": 0
						},
						{
							"origin": [
								-7.35438,
								19.3576,
								-1.82422
							],
							"size": [
								3.53126,
								4.5144,
								3.75197
							],
							"uv": {
								"north": {
									"uv": [
										6,
										5.5
									],
									"uv_size": [
										0.5,
										0.625
									]
								},
								"east": {
									"uv": [
										1.375,
										6.25
									],
									"uv_size": [
										0.5,
										0.625
									]
								},
								"south": {
									"uv": [
										6,
										5.5
									],
									"uv_size": [
										0.5,
										0.625
									]
								},
								"west": {
									"uv": [
										1.375,
										6.25
									],
									"uv_size": [
										0.5,
										0.625
									]
								},
								"up": {
									"uv": [
										2.875,
										7.125
									],
									"uv_size": [
										-0.5,
										-0.5
									]
								},
								"down": {
									"uv": [
										2.875,
										7.125
									],
									"uv_size": [
										-0.5,
										-0.5
									]
								}
							},
							"inflate": 0
						}
					],
					"parent": "RightArm"
				},
				{
					"name": "bone22",
					"pivot": [
						-6.09222,
						22.1594,
						-0.0292
					],
					"cubes": [
						{
							"origin": [
								-6.64,
								15.248,
								-1.204
							],
							"size": [
								2.288,
								4.4,
								2.288
							],
							"uv": {
								"north": {
									"uv": [
										5.375,
										1
									],
									"uv_size": [
										0.375,
										0.5
									]
								},
								"east": {
									"uv": [
										5.375,
										1
									],
									"uv_size": [
										0.375,
										0.5
									]
								},
								"south": {
									"uv": [
										5.375,
										1
									],
									"uv_size": [
										0.375,
										0.5
									]
								},
								"west": {
									"uv": [
										5.375,
										1
									],
									"uv_size": [
										0.375,
										0.5
									]
								},
								"up": {
									"uv": [
										5.75,
										1.5
									],
									"uv_size": [
										-0.375,
										-0.5
									]
								},
								"down": {
									"uv": [
										5.75,
										1.5
									],
									"uv_size": [
										-0.375,
										-0.5
									]
								}
							},
							"inflate": 0
						},
						{
							"origin": [
								-7.05342,
								14.3416,
								-1.62358
							],
							"size": [
								3.12998,
								4.5144,
								3.25037
							],
							"uv": {
								"north": {
									"uv": [
										7.125,
										4
									],
									"uv_size": [
										-0.375,
										0.625
									]
								},
								"east": {
									"uv": [
										8.875,
										4.5
									],
									"uv_size": [
										0.375,
										0.625
									]
								},
								"south": {
									"uv": [
										6.75,
										4
									],
									"uv_size": [
										0.375,
										0.625
									]
								},
								"west": {
									"uv": [
										8.875,
										4.5
									],
									"uv_size": [
										0.375,
										0.625
									]
								},
								"up": {
									"uv": [
										7.75,
										5.5
									],
									"uv_size": [
										-0.375,
										-0.375
									]
								},
								"down": {
									"uv": [
										7.75,
										5.5
									],
									"uv_size": [
										-0.375,
										-0.375
									]
								}
							},
							"inflate": 0
						}
					],
					"parent": "bone23"
				},
				{
					"name": "bone21",
					"pivot": [
						-5.98184,
						17.15733,
						-0.02896
					],
					"cubes": [
						{
							"origin": [
								-6.64,
								12.608,
								-1.204
							],
							"size": [
								2.288,
								3.344,
								2.288
							],
							"uv": {
								"north": {
									"uv": [
										5.375,
										1
									],
									"uv_size": [
										0.375,
										0.5
									]
								},
								"east": {
									"uv": [
										5.375,
										1
									],
									"uv_size": [
										0.375,
										0.5
									]
								},
								"south": {
									"uv": [
										5.375,
										1
									],
									"uv_size": [
										0.375,
										0.5
									]
								},
								"west": {
									"uv": [
										5.375,
										1
									],
									"uv_size": [
										0.375,
										0.5
									]
								},
								"up": {
									"uv": [
										5.75,
										1.5
									],
									"uv_size": [
										-0.375,
										-0.5
									]
								},
								"down": {
									"uv": [
										5.75,
										1.5
									],
									"uv_size": [
										-0.375,
										-0.5
									]
								}
							},
							"inflate": 0
						},
						{
							"origin": [
								-7.26638,
								12.3352,
								-1.82422
							],
							"size": [
								3.53126,
								1.5048,
								3.75197
							],
							"uv": {
								"north": {
									"uv": [
										6.25,
										2.25
									],
									"uv_size": [
										0.5,
										0.25
									]
								},
								"east": {
									"uv": [
										7.375,
										6.25
									],
									"uv_size": [
										0.5,
										0.25
									]
								},
								"south": {
									"uv": [
										7.5,
										1.75
									],
									"uv_size": [
										0.5,
										0.25
									]
								},
								"west": {
									"uv": [
										3.75,
										7.5
									],
									"uv_size": [
										0.5,
										0.25
									]
								},
								"up": {
									"uv": [
										6.25,
										5
									],
									"uv_size": [
										0.5,
										0.5
									]
								},
								"down": {
									"uv": [
										6.375,
										0.5
									],
									"uv_size": [
										0.5,
										-0.5
									]
								}
							},
							"inflate": 0
						},
						{
							"origin": [
								-6.91438,
								7.6976,
								-0.07866
							],
							"size": [
								3.53126,
								4.6376,
								0
							],
							"uv": {
								"north": {
									"uv": [
										0.25,
										11.75
									],
									"uv_size": [
										1.25,
										1.5
									]
								},
								"east": {
									"uv": [
										0,
										0
									],
									"uv_size": [
										0,
										0.75
									]
								},
								"south": {
									"uv": [
										5.75,
										1.75
									],
									"uv_size": [
										0.5,
										0.75
									]
								},
								"west": {
									"uv": [
										0,
										0
									],
									"uv_size": [
										0,
										0.75
									]
								},
								"up": {
									"uv": [
										0,
										0
									],
									"uv_size": [
										0.5,
										0
									]
								},
								"down": {
									"uv": [
										0,
										0
									],
									"uv_size": [
										0.5,
										0
									]
								}
							},
							"inflate": 0
						}
					],
					"parent": "bone22"
				},
				{
					"name": "LeftArm",
					"pivot": [
						5,
						22,
						0
					]
				},
				{
					"name": "bone26",
					"pivot": [
						7,
						22.2,
						-0.5
					],
					"cubes": [
						{
							"origin": [
								3.75597,
								19.3576,
								-1.82422
							],
							"size": [
								3.53126,
								4.5144,
								3.75197
							],
							"uv": {
								"north": {
									"uv": [
										6.5,
										5.5
									],
									"uv_size": [
										-0.5,
										0.625
									]
								},
								"east": {
									"uv": [
										1.875,
										6.25
									],
									"uv_size": [
										-0.5,
										0.625
									]
								},
								"south": {
									"uv": [
										1.375,
										6.25
									],
									"uv_size": [
										-0.5,
										0.625
									]
								},
								"west": {
									"uv": [
										6.5,
										6.125
									],
									"uv_size": [
										-0.5,
										0.625
									]
								},
								"up": {
									"uv": [
										2.875,
										6.625
									],
									"uv_size": [
										-0.5,
										0.5
									]
								},
								"down": {
									"uv": [
										2.875,
										7.125
									],
									"uv_size": [
										-0.5,
										-0.5
									]
								}
							},
							"inflate": 0
						},
						{
							"origin": [
								4.448,
								20.528,
								-1.204
							],
							"size": [
								2.288,
								4.4,
								2.288
							],
							"uv": {
								"north": {
									"uv": [
										5.375,
										1
									],
									"uv_size": [
										0.375,
										0.5
									]
								},
								"east": {
									"uv": [
										5.375,
										1
									],
									"uv_size": [
										0.375,
										0.5
									]
								},
								"south": {
									"uv": [
										5.375,
										1
									],
									"uv_size": [
										0.375,
										0.5
									]
								},
								"west": {
									"uv": [
										5.375,
										1
									],
									"uv_size": [
										0.375,
										0.5
									]
								},
								"up": {
									"uv": [
										5.75,
										1.5
									],
									"uv_size": [
										-0.375,
										-0.5
									]
								},
								"down": {
									"uv": [
										5.75,
										1.5
									],
									"uv_size": [
										-0.375,
										-0.5
									]
								}
							},
							"inflate": 0
						}
					],
					"parent": "LeftArm"
				},
				{
					"name": "bone25",
					"pivot": [
						3.20778,
						22.1594,
						-0.0292
					],
					"cubes": [
						{
							"origin": [
								4.448,
								12.608,
								-1.204
							],
							"size": [
								2.288,
								4.4,
								2.288
							],
							"uv": {
								"north": {
									"uv": [
										5.75,
										1
									],
									"uv_size": [
										-0.375,
										0.5
									]
								},
								"east": {
									"uv": [
										5.75,
										1
									],
									"uv_size": [
										-0.375,
										0.5
									]
								},
								"south": {
									"uv": [
										5.75,
										1
									],
									"uv_size": [
										-0.375,
										0.5
									]
								},
								"west": {
									"uv": [
										5.75,
										1
									],
									"uv_size": [
										-0.375,
										0.5
									]
								},
								"up": {
									"uv": [
										5.375,
										1.5
									],
									"uv_size": [
										0.375,
										-0.5
									]
								},
								"down": {
									"uv": [
										5.375,
										1.5
									],
									"uv_size": [
										0.375,
										-0.5
									]
								}
							},
							"inflate": 0
						},
						{
							"origin": [
								4.448,
								17.008,
								-1.204
							],
							"size": [
								2.288,
								4.4,
								2.288
							],
							"uv": {
								"north": {
									"uv": [
										5.75,
										1
									],
									"uv_size": [
										-0.375,
										0.5
									]
								},
								"east": {
									"uv": [
										5.75,
										1
									],
									"uv_size": [
										-0.375,
										0.5
									]
								},
								"south": {
									"uv": [
										5.75,
										1
									],
									"uv_size": [
										-0.375,
										0.5
									]
								},
								"west": {
									"uv": [
										5.75,
										1
									],
									"uv_size": [
										-0.375,
										0.5
									]
								},
								"up": {
									"uv": [
										5.375,
										1.5
									],
									"uv_size": [
										0.375,
										-0.5
									]
								},
								"down": {
									"uv": [
										5.375,
										1.5
									],
									"uv_size": [
										0.375,
										-0.5
									]
								}
							},
							"inflate": 0
						},
						{
							"origin": [
								4.05693,
								14.3416,
								-1.62358
							],
							"size": [
								3.12998,
								4.5144,
								3.25037
							],
							"uv": {
								"north": {
									"uv": [
										7.125,
										4
									],
									"uv_size": [
										-0.375,
										0.625
									]
								},
								"east": {
									"uv": [
										8.875,
										4.5
									],
									"uv_size": [
										0.375,
										0.625
									]
								},
								"south": {
									"uv": [
										6.75,
										4
									],
									"uv_size": [
										0.375,
										0.625
									]
								},
								"west": {
									"uv": [
										9.25,
										4.5
									],
									"uv_size": [
										-0.375,
										0.625
									]
								},
								"up": {
									"uv": [
										7.375,
										5.5
									],
									"uv_size": [
										0.375,
										-0.375
									]
								},
								"down": {
									"uv": [
										6.75,
										4.625
									],
									"uv_size": [
										0.375,
										-0.625
									]
								}
							},
							"inflate": 0
						}
					],
					"parent": "bone26"
				},
				{
					"name": "bone24",
					"pivot": [
						3.31814,
						17.1573,
						-0.02894
					],
					"cubes": [
						{
							"origin": [
								3.75597,
								10.3288,
								-1.82422
							],
							"size": [
								3.53126,
								3.5112,
								3.75197
							],
							"uv": {
								"north": {
									"uv": [
										0.875,
										6.5
									],
									"uv_size": [
										-0.5,
										0.5
									]
								},
								"east": {
									"uv": [
										7,
										6.5
									],
									"uv_size": [
										-0.5,
										0.5
									]
								},
								"south": {
									"uv": [
										7,
										6
									],
									"uv_size": [
										-0.5,
										0.5
									]
								},
								"west": {
									"uv": [
										7,
										5.5
									],
									"uv_size": [
										-0.5,
										0.5
									]
								},
								"up": {
									"uv": [
										7.125,
										0.5
									],
									"uv_size": [
										-0.5,
										0.5
									]
								},
								"down": {
									"uv": [
										2.375,
										7.125
									],
									"uv_size": [
										-0.5,
										-0.5
									]
								}
							},
							"inflate": 0
						}
					],
					"parent": "bone25"
				},
				{
					"name": "RightLeg",
					"pivot": [
						-1.9,
						12,
						0
					]
				},
				{
					"name": "bone2",
					"pivot": [
						-2.0375,
						12.65,
						0.45
					],
					"cubes": [
						{
							"origin": [
								-3.11,
								0.85,
								-0.45
							],
							"size": [
								1.8,
								11.7,
								1.8
							],
							"uv": {
								"north": {
									"uv": [
										3,
										4.375
									],
									"uv_size": [
										-0.375,
										1.875
									]
								},
								"east": {
									"uv": [
										3,
										4.375
									],
									"uv_size": [
										-0.375,
										1.875
									]
								},
								"south": {
									"uv": [
										3,
										4.375
									],
									"uv_size": [
										-0.375,
										1.875
									]
								},
								"west": {
									"uv": [
										3,
										4.375
									],
									"uv_size": [
										-0.375,
										1.875
									]
								},
								"up": {
									"uv": [
										9.125,
										3.375
									],
									"uv_size": [
										0.625,
										-0.625
									]
								},
								"down": {
									"uv": [
										2.625,
										6.25
									],
									"uv_size": [
										0.375,
										-1.875
									]
								}
							},
							"inflate": 0
						},
						{
							"origin": [
								-4.055,
								6.75,
								-1.575
							],
							"size": [
								3.6,
								4.2,
								4.05
							],
							"uv": {
								"north": {
									"uv": [
										2.25,
										0.5
									],
									"uv_size": [
										0.625,
										0.625
									]
								},
								"east": {
									"uv": [
										2,
										0.5
									],
									"uv_size": [
										-0.625,
										0.625
									]
								},
								"south": {
									"uv": [
										2.875,
										1.625
									],
									"uv_size": [
										-0.625,
										0.625
									]
								},
								"west": {
									"uv": [
										2,
										1.625
									],
									"uv_size": [
										-0.625,
										0.625
									]
								},
								"up": {
									"uv": [
										8.625,
										3.875
									],
									"uv_size": [
										0.625,
										-0.625
									]
								},
								"down": {
									"uv": [
										9.875,
										3.875
									],
									"uv_size": [
										-0.625,
										-0.625
									]
								}
							},
							"inflate": 0
						},
						{
							"origin": [
								-4.055,
								1.8,
								-1.575
							],
							"size": [
								3.6,
								4.5,
								4.05
							],
							"uv": {
								"north": {
									"uv": [
										4.75,
										3.75
									],
									"uv_size": [
										-0.625,
										0.625
									]
								},
								"east": {
									"uv": [
										4.75,
										3.75
									],
									"uv_size": [
										-0.625,
										0.625
									]
								},
								"south": {
									"uv": [
										4.125,
										3.75
									],
									"uv_size": [
										0.625,
										0.625
									]
								},
								"west": {
									"uv": [
										4.75,
										3.75
									],
									"uv_size": [
										-0.625,
										0.625
									]
								},
								"up": {
									"uv": [
										9.25,
										3.875
									],
									"uv_size": [
										0.625,
										-0.625
									]
								},
								"down": {
									"uv": [
										9.875,
										3.875
									],
									"uv_size": [
										-0.625,
										-0.625
									]
								}
							},
							"inflate": 0
						}
					],
					"parent": "RightLeg"
				},
				{
					"name": "bone3",
					"pivot": [
						-1.88,
						0.05,
						0.54
					],
					"cubes": [
						{
							"origin": [
								-4.46,
								-0.45,
								-4.5
							],
							"size": [
								4.5,
								1.8,
								7.2
							],
							"uv": {
								"north": {
									"uv": [
										7.375,
										1.125
									],
									"uv_size": [
										-0.625,
										0.25
									]
								},
								"east": {
									"uv": [
										6.75,
										1.5
									],
									"uv_size": [
										-1,
										0.25
									]
								},
								"south": {
									"uv": [
										7.375,
										1.5
									],
									"uv_size": [
										-0.625,
										0.25
									]
								},
								"west": {
									"uv": [
										6.75,
										1.125
									],
									"uv_size": [
										-1,
										0.25
									]
								},
								"up": {
									"uv": [
										5.75,
										4.625
									],
									"uv_size": [
										-0.625,
										1
									]
								},
								"down": {
									"uv": [
										5.875,
										1
									],
									"uv_size": [
										-0.625,
										-1
									]
								}
							},
							"inflate": 0
						}
					],
					"parent": "bone2"
				},
				{
					"name": "LeftLeg",
					"pivot": [
						1.9,
						12,
						0
					]
				},
				{
					"name": "bone5",
					"pivot": [
						2.0375,
						12.65,
						0.45
					],
					"cubes": [
						{
							"origin": [
								1.31,
								0.85,
								-0.45
							],
							"size": [
								1.8,
								11.7,
								1.8
							],
							"uv": {
								"north": {
									"uv": [
										2.625,
										4.375
									],
									"uv_size": [
										0.375,
										1.875
									]
								},
								"east": {
									"uv": [
										2.625,
										4.375
									],
									"uv_size": [
										0.375,
										1.875
									]
								},
								"south": {
									"uv": [
										2.625,
										4.375
									],
									"uv_size": [
										0.375,
										1.875
									]
								},
								"west": {
									"uv": [
										2.625,
										4.375
									],
									"uv_size": [
										0.375,
										1.875
									]
								},
								"up": {
									"uv": [
										9.75,
										3.375
									],
									"uv_size": [
										-0.625,
										-0.625
									]
								},
								"down": {
									"uv": [
										3,
										6.25
									],
									"uv_size": [
										-0.375,
										-1.875
									]
								}
							},
							"inflate": 0
						},
						{
							"origin": [
								0.455,
								6.75,
								-1.575
							],
							"size": [
								3.6,
								4.2,
								4.05
							],
							"uv": {
								"north": {
									"uv": [
										2.875,
										0.5
									],
									"uv_size": [
										-0.625,
										0.625
									]
								},
								"east": {
									"uv": [
										1.375,
										1.625
									],
									"uv_size": [
										0.625,
										0.625
									]
								},
								"south": {
									"uv": [
										2.25,
										1.625
									],
									"uv_size": [
										0.625,
										0.625
									]
								},
								"west": {
									"uv": [
										1.375,
										0.5
									],
									"uv_size": [
										0.625,
										0.625
									]
								},
								"up": {
									"uv": [
										9.25,
										3.875
									],
									"uv_size": [
										-0.625,
										-0.625
									]
								},
								"down": {
									"uv": [
										9.25,
										3.875
									],
									"uv_size": [
										0.625,
										-0.625
									]
								}
							},
							"inflate": 0
						},
						{
							"origin": [
								0.455,
								1.8,
								-1.575
							],
							"size": [
								3.6,
								4.5,
								4.05
							],
							"uv": {
								"north": {
									"uv": [
										4.125,
										3.75
									],
									"uv_size": [
										0.625,
										0.625
									]
								},
								"east": {
									"uv": [
										4.125,
										3.75
									],
									"uv_size": [
										0.625,
										0.625
									]
								},
								"south": {
									"uv": [
										4.75,
										3.75
									],
									"uv_size": [
										-0.625,
										0.625
									]
								},
								"west": {
									"uv": [
										4.125,
										3.75
									],
									"uv_size": [
										0.625,
										0.625
									]
								},
								"up": {
									"uv": [
										9.875,
										3.875
									],
									"uv_size": [
										-0.625,
										-0.625
									]
								},
								"down": {
									"uv": [
										9.25,
										3.875
									],
									"uv_size": [
										0.625,
										-0.625
									]
								}
							},
							"inflate": 0
						}
					],
					"parent": "LeftLeg"
				},
				{
					"name": "bone4",
					"pivot": [
						1.88,
						0.05,
						0.54
					],
					"cubes": [
						{
							"origin": [
								-0.04,
								-0.45,
								-4.5
							],
							"size": [
								4.5,
								1.8,
								7.2
							],
							"uv": {
								"north": {
									"uv": [
										6.75,
										1.125
									],
									"uv_size": [
										0.625,
										0.25
									]
								},
								"east": {
									"uv": [
										5.75,
										1.125
									],
									"uv_size": [
										1,
										0.25
									]
								},
								"south": {
									"uv": [
										6.75,
										1.5
									],
									"uv_size": [
										0.625,
										0.25
									]
								},
								"west": {
									"uv": [
										5.75,
										1.5
									],
									"uv_size": [
										1,
										0.25
									]
								},
								"up": {
									"uv": [
										5.125,
										4.625
									],
									"uv_size": [
										0.625,
										1
									]
								},
								"down": {
									"uv": [
										5.25,
										1
									],
									"uv_size": [
										0.625,
										-1
									]
								}
							},
							"inflate": 0
						}
					],
					"parent": "bone5"
				},
				{
					"name": "head",
					"pivot": [
						0,
						24,
						0
					]
				},
				{
					"name": "head2",
					"pivot": [
						0,
						-6.75,
						0
					],
					"parent": "head",
					"rotation": [
						-17.5,
						0,
						0
					]
				},
				{
					"name": "head_up",
					"pivot": [
						-0.04951,
						27.78554,
						-6.82448
					],
					"cubes": [
						{
							"origin": [
								-3.42943,
								27.86369,
								-13.75341
							],
							"size": [
								6.76206,
								6.03955,
								6.76206
							],
							"pivot": [
								-0.01285,
								27.9484,
								-7.06095
							],
							"rotation": [
								17.5,
								0,
								0
							],
							"uv": {
								"north": {
									"uv": [
										4.375,
										0
									],
									"uv_size": [
										0.875,
										0.75
									]
								},
								"east": {
									"uv": [
										0,
										5
									],
									"uv_size": [
										0.875,
										0.75
									]
								},
								"south": {
									"uv": [
										4.75,
										12.75
									],
									"uv_size": [
										0.875,
										0.75
									]
								},
								"west": {
									"uv": [
										4.75,
										12.75
									],
									"uv_size": [
										0.875,
										0.75
									]
								},
								"up": {
									"uv": [
										0,
										3.5
									],
									"uv_size": [
										0.875,
										0.875
									]
								},
								"down": {
									"uv": [
										1.75,
										4.375
									],
									"uv_size": [
										0.875,
										-0.875
									]
								}
							},
							"inflate": 0
						},
						{
							"origin": [
								-1.95342,
								25.01976,
								-14.52669
							],
							"size": [
								3.6513,
								2.87302,
								2.55552
							],
							"pivot": [
								-0.0484,
								28.94418,
								-11.88077
							],
							"rotation": [
								17.5,
								0,
								0
							],
							"uv": {
								"north": {
									"uv": [
										2.75,
										9.125
									],
									"uv_size": [
										1,
										0.5
									]
								},
								"east": {
									"uv": [
										2.25,
										9.125
									],
									"uv_size": [
										0.5,
										0.5
									]
								},
								"south": {
									"uv": [
										2.25,
										9.125
									],
									"uv_size": [
										0.5,
										0.5
									]
								},
								"west": {
									"uv": [
										2.75,
										9.125
									],
									"uv_size": [
										-0.5,
										0.5
									]
								},
								"up": {
									"uv": [
										3.75,
										9.125
									],
									"uv_size": [
										-1,
										0.25
									]
								},
								"down": {
									"uv": [
										3.75,
										9.375
									],
									"uv_size": [
										-1,
										-0.25
									]
								}
							},
							"inflate": 0
						},
						{
							"origin": [
								-2.34256,
								28.69412,
								-13.72207
							],
							"size": [
								1.82565,
								1.90502,
								1.58752
							],
							"pivot": [
								-1.42974,
								29.47872,
								-11.93782
							],
							"rotation": [
								17.5,
								0,
								0
							],
							"uv": {
								"north": {
									"uv": [
										11.125,
										7.875
									],
									"uv_size": [
										0.5,
										0.5
									]
								},
								"east": {
									"uv": [
										10.625,
										7.875
									],
									"uv_size": [
										0.5,
										0.5
									]
								},
								"south": {
									"uv": [
										10.625,
										7.875
									],
									"uv_size": [
										0.5,
										0.5
									]
								},
								"west": {
									"uv": [
										10.625,
										7.875
									],
									"uv_size": [
										0.5,
										0.5
									]
								},
								"up": {
									"uv": [
										11.125,
										8.375
									],
									"uv_size": [
										-0.5,
										-0.5
									]
								},
								"down": {
									"uv": [
										11.125,
										8.375
									],
									"uv_size": [
										-0.5,
										-0.5
									]
								}
							},
							"inflate": 0
						},
						{
							"origin": [
								0.46464,
								28.69412,
								-13.72207
							],
							"size": [
								1.82565,
								1.90502,
								1.58752
							],
							"pivot": [
								-1.42974,
								29.47872,
								-11.93782
							],
							"rotation": [
								17.5,
								0,
								0
							],
							"uv": {
								"north": {
									"uv": [
										11.125,
										7.875
									],
									"uv_size": [
										0.5,
										0.5
									]
								},
								"east": {
									"uv": [
										10.625,
										7.875
									],
									"uv_size": [
										0.5,
										0.5
									]
								},
								"south": {
									"uv": [
										10.625,
										7.875
									],
									"uv_size": [
										0.5,
										0.5
									]
								},
								"west": {
									"uv": [
										10.625,
										7.875
									],
									"uv_size": [
										0.5,
										0.5
									]
								},
								"up": {
									"uv": [
										11.125,
										8.375
									],
									"uv_size": [
										-0.5,
										-0.5
									]
								},
								"down": {
									"uv": [
										11.125,
										8.375
									],
									"uv_size": [
										-0.5,
										-0.5
									]
								}
							},
							"inflate": 0
						},
						{
							"origin": [
								0.43754,
								29.43043,
								-14.1158
							],
							"size": [
								1.9844,
								1.19064,
								1.9844
							],
							"pivot": [
								1.42974,
								29.72221,
								-12.21958
							],
							"rotation": [
								-5,
								0,
								0
							],
							"uv": {
								"north": {
									"uv": [
										10.875,
										10.375
									],
									"uv_size": [
										0,
										0.25
									]
								},
								"east": {
									"uv": [
										10.875,
										10.375
									],
									"uv_size": [
										0,
										0.25
									]
								},
								"south": {
									"uv": [
										10.875,
										10.375
									],
									"uv_size": [
										0,
										0.25
									]
								},
								"west": {
									"uv": [
										10.875,
										10.375
									],
									"uv_size": [
										0,
										0.25
									]
								},
								"up": {
									"uv": [
										10.875,
										10.625
									],
									"uv_size": [
										0,
										-0.25
									]
								},
								"down": {
									"uv": [
										10.875,
										10.625
									],
									"uv_size": [
										0,
										-0.25
									]
								}
							},
							"inflate": 0
						},
						{
							"origin": [
								-2.42194,
								29.40495,
								-14.13595
							],
							"size": [
								1.9844,
								1.19064,
								1.9844
							],
							"pivot": [
								-1.42974,
								29.47872,
								-11.93782
							],
							"rotation": [
								-5,
								0,
								0
							],
							"uv": {
								"north": {
									"uv": [
										10.75,
										10.375
									],
									"uv_size": [
										0.25,
										0.25
									]
								},
								"east": {
									"uv": [
										10.75,
										10.375
									],
									"uv_size": [
										0.25,
										0.25
									]
								},
								"south": {
									"uv": [
										10.75,
										10.375
									],
									"uv_size": [
										0.25,
										0.25
									]
								},
								"west": {
									"uv": [
										10.75,
										10.375
									],
									"uv_size": [
										0.25,
										0.25
									]
								},
								"up": {
									"uv": [
										11,
										10.625
									],
									"uv_size": [
										-0.25,
										-0.25
									]
								},
								"down": {
									"uv": [
										11,
										10.625
									],
									"uv_size": [
										-0.25,
										-0.25
									]
								}
							},
							"inflate": 0
						},
						{
							"origin": [
								-2.73944,
								25.51684,
								-11.26892
							],
							"size": [
								5.38208,
								7.63558,
								3.17504
							],
							"pivot": [
								-0.0484,
								27.07019,
								-8.88342
							],
							"rotation": [
								17.5,
								0,
								0
							],
							"uv": {
								"north": {
									"uv": [
										0,
										8.5
									],
									"uv_size": [
										1.5,
										1.125
									]
								},
								"east": {
									"uv": [
										1.5,
										8.5
									],
									"uv_size": [
										0.5,
										1.125
									]
								},
								"south": {
									"uv": [
										0,
										8.5
									],
									"uv_size": [
										1.5,
										1.125
									]
								},
								"west": {
									"uv": [
										2,
										8.5
									],
									"uv_size": [
										-0.5,
										1.125
									]
								},
								"up": {
									"uv": [
										1.5,
										10.25
									],
									"uv_size": [
										-1.5,
										-0.625
									]
								},
								"down": {
									"uv": [
										1.5,
										10.25
									],
									"uv_size": [
										-1.5,
										-0.625
									]
								}
							},
							"inflate": 0
						},
						{
							"origin": [
								-1.97743,
								33.28449,
								-10.86335
							],
							"size": [
								3.85806,
								2.16755,
								0
							],
							"pivot": [
								-0.01285,
								27.9484,
								-7.06095
							],
							"rotation": [
								17.5,
								0,
								0
							],
							"uv": {
								"north": {
									"uv": [
										6.875,
										0
									],
									"uv_size": [
										0.625,
										0.375
									]
								},
								"east": {
									"uv": [
										9.625,
										1.875
									],
									"uv_size": [
										0.625,
										0.375
									]
								},
								"south": {
									"uv": [
										9.625,
										1.875
									],
									"uv_size": [
										0.625,
										0.375
									]
								},
								"west": {
									"uv": [
										9.625,
										1.875
									],
									"uv_size": [
										0.625,
										0.375
									]
								},
								"up": {
									"uv": [
										10.25,
										2.25
									],
									"uv_size": [
										-0.625,
										-0.375
									]
								},
								"down": {
									"uv": [
										10.25,
										2.25
									],
									"uv_size": [
										-0.625,
										-0.375
									]
								}
							},
							"inflate": 0
						},
						{
							"origin": [
								-6.68846,
								27.77186,
								-11.64604
							],
							"size": [
								3.60012,
								3.00034,
								0.984
							],
							"pivot": [
								-0.01285,
								27.9484,
								-7.06095
							],
							"rotation": [
								17.5,
								0,
								0
							],
							"uv": {
								"north": {
									"uv": [
										7.375,
										5.875
									],
									"uv_size": [
										0.375,
										0.375
									]
								},
								"east": {
									"uv": [
										2.625,
										3.75
									],
									"uv_size": [
										0.125,
										0.375
									]
								},
								"south": {
									"uv": [
										6.125,
										7.375
									],
									"uv_size": [
										0.375,
										0.375
									]
								},
								"west": {
									"uv": [
										2.75,
										3.75
									],
									"uv_size": [
										0.125,
										0.375
									]
								},
								"up": {
									"uv": [
										5.25,
										2.5
									],
									"uv_size": [
										0.375,
										0.125
									]
								},
								"down": {
									"uv": [
										7.625,
										4.625
									],
									"uv_size": [
										0.375,
										-0.125
									]
								}
							},
							"inflate": -0.25
						},
						{
							"origin": [
								3.08834,
								25.85281,
								-12.0561
							],
							"size": [
								3.60012,
								3.00034,
								0.984
							],
							"pivot": [
								4.4528,
								28.32098,
								-13.5001
							],
							"rotation": [
								17.5,
								0,
								0
							],
							"uv": {
								"north": {
									"uv": [
										6.5,
										7.375
									],
									"uv_size": [
										0.375,
										0.375
									]
								},
								"east": {
									"uv": [
										3.375,
										4.375
									],
									"uv_size": [
										0.125,
										0.375
									]
								},
								"south": {
									"uv": [
										7.375,
										7.25
									],
									"uv_size": [
										0.375,
										0.375
									]
								},
								"west": {
									"uv": [
										4.625,
										4.875
									],
									"uv_size": [
										0.125,
										0.375
									]
								},
								"up": {
									"uv": [
										7.625,
										6.625
									],
									"uv_size": [
										0.375,
										0.125
									]
								},
								"down": {
									"uv": [
										7.625,
										6.875
									],
									"uv_size": [
										0.375,
										-0.125
									]
								}
							},
							"inflate": -0.25
						}
					],
					"parent": "head2"
				},
				{
					"name": "bone20",
					"pivot": [
						0,
						26.59575,
						-13.66888
					],
					"cubes": [
						{
							"origin": [
								-2.67126,
								25.52861,
								-17.54673
							],
							"size": [
								5.34252,
								2.80674,
								4.35554
							],
							"uv": {
								"north": {
									"uv": [
										5.875,
										0.625
									],
									"uv_size": [
										0.75,
										0.375
									]
								},
								"east": {
									"uv": [
										7.375,
										5.5
									],
									"uv_size": [
										0.375,
										0.375
									]
								},
								"south": {
									"uv": [
										1.875,
										6.25
									],
									"uv_size": [
										0.75,
										0.375
									]
								},
								"west": {
									"uv": [
										5.75,
										7.375
									],
									"uv_size": [
										0.375,
										0.375
									]
								},
								"up": {
									"uv": [
										2.625,
										6.25
									],
									"uv_size": [
										0.75,
										0.375
									]
								},
								"down": {
									"uv": [
										6.25,
										4
									],
									"uv_size": [
										0.75,
										-0.375
									]
								}
							},
							"inflate": -0.25
						},
						{
							"origin": [
								-2.57446,
								24.56061,
								-17.44993
							],
							"size": [
								5.14892,
								1.45154,
								4.25874
							],
							"uv": {
								"north": {
									"uv": [
										7.375,
										8.875
									],
									"uv_size": [
										0.625,
										0.125
									]
								},
								"east": {
									"uv": [
										6.875,
										9
									],
									"uv_size": [
										0.375,
										0.125
									]
								},
								"south": {
									"uv": [
										10.375,
										8.125
									],
									"uv_size": [
										0.75,
										0.375
									]
								},
								"west": {
									"uv": [
										6.375,
										9
									],
									"uv_size": [
										0.375,
										0.125
									]
								},
								"up": {
									"uv": [
										11,
										5.75
									],
									"uv_size": [
										0.75,
										0.375
									]
								},
								"down": {
									"uv": [
										11,
										6.125
									],
									"uv_size": [
										0.75,
										-0.375
									]
								}
							},
							"inflate": -0.25
						},
						{
							"origin": [
								-0.968,
								26.98295,
								-17.54088
							],
							"size": [
								1.936,
								1.3552,
								1.452
							],
							"uv": {
								"north": {
									"uv": [
										5.125,
										8.625
									],
									"uv_size": [
										0.25,
										0.175
									]
								},
								"east": {
									"uv": [
										5.125,
										8.625
									],
									"uv_size": [
										0.25,
										0.175
									]
								},
								"south": {
									"uv": [
										5.125,
										8.625
									],
									"uv_size": [
										0.25,
										0.175
									]
								},
								"west": {
									"uv": [
										5.125,
										8.625
									],
									"uv_size": [
										0.25,
										0.175
									]
								},
								"up": {
									"uv": [
										5.125,
										8.8
									],
									"uv_size": [
										0.25,
										-0.175
									]
								},
								"down": {
									"uv": [
										5.375,
										8.8
									],
									"uv_size": [
										-0.25,
										-0.175
									]
								}
							},
							"inflate": 0
						}
					],
					"parent": "head_up",
					"rotation": [
						17.5,
						0,
						0
					]
				},
				{
					"name": "freddy_ear4",
					"pivot": [
						-3.13359,
						32.94096,
						-10.62596
					],
					"cubes": [
						{
							"origin": [
								-7.25054,
								31.12391,
								-11.16864
							],
							"size": [
								3.87154,
								3.38754,
								0.92263
							],
							"uv": {
								"north": {
									"uv": [
										3.75,
										7.125
									],
									"uv_size": [
										0.5,
										0.375
									]
								},
								"east": {
									"uv": [
										0.875,
										5
									],
									"uv_size": [
										0.125,
										0.375
									]
								},
								"south": {
									"uv": [
										7.125,
										4
									],
									"uv_size": [
										0.5,
										0.375
									]
								},
								"west": {
									"uv": [
										1,
										5
									],
									"uv_size": [
										0.125,
										0.375
									]
								},
								"up": {
									"uv": [
										7.625,
										4
									],
									"uv_size": [
										0.5,
										0.125
									]
								},
								"down": {
									"uv": [
										7.625,
										4.25
									],
									"uv_size": [
										0.5,
										-0.125
									]
								}
							},
							"inflate": -0.25
						},
						{
							"origin": [
								-5.27616,
								31.65723,
								-10.87202
							],
							"size": [
								2.61314,
								2.61314,
								0.92263
							],
							"uv": {
								"north": {
									"uv": [
										7.5,
										0
									],
									"uv_size": [
										0.375,
										0.375
									]
								},
								"east": {
									"uv": [
										5.25,
										1.875
									],
									"uv_size": [
										0.125,
										0.375
									]
								},
								"south": {
									"uv": [
										0.75,
										7.5
									],
									"uv_size": [
										0.375,
										0.375
									]
								},
								"west": {
									"uv": [
										4.625,
										5.25
									],
									"uv_size": [
										0.125,
										0.375
									]
								},
								"up": {
									"uv": [
										6.875,
										7.625
									],
									"uv_size": [
										0.375,
										0.125
									]
								},
								"down": {
									"uv": [
										7.625,
										7
									],
									"uv_size": [
										0.375,
										-0.125
									]
								}
							},
							"inflate": -0.25
						}
					],
					"parent": "head_up",
					"rotation": [
						2.35667,
						-17.34552,
						54.64047
					]
				},
				{
					"name": "freddy_ear3",
					"pivot": [
						3.03679,
						32.94096,
						-10.62596
					],
					"cubes": [
						{
							"origin": [
								3.28219,
								31.12391,
								-11.16864
							],
							"size": [
								3.87154,
								3.38754,
								0.92263
							],
							"uv": {
								"north": {
									"uv": [
										4.25,
										7.125
									],
									"uv_size": [
										-0.5,
										0.375
									]
								},
								"east": {
									"uv": [
										1.125,
										5
									],
									"uv_size": [
										-0.125,
										0.375
									]
								},
								"south": {
									"uv": [
										7.625,
										4
									],
									"uv_size": [
										-0.5,
										0.375
									]
								},
								"west": {
									"uv": [
										1,
										5
									],
									"uv_size": [
										-0.125,
										0.375
									]
								},
								"up": {
									"uv": [
										8.125,
										4
									],
									"uv_size": [
										-0.5,
										0.125
									]
								},
								"down": {
									"uv": [
										8.125,
										4.25
									],
									"uv_size": [
										-0.5,
										-0.125
									]
								}
							},
							"inflate": -0.25
						},
						{
							"origin": [
								2.56621,
								31.65723,
								-10.87202
							],
							"size": [
								2.61314,
								2.61314,
								0.92263
							],
							"uv": {
								"north": {
									"uv": [
										7.875,
										0
									],
									"uv_size": [
										-0.375,
										0.375
									]
								},
								"east": {
									"uv": [
										4.75,
										5.25
									],
									"uv_size": [
										-0.125,
										0.375
									]
								},
								"south": {
									"uv": [
										1.125,
										7.5
									],
									"uv_size": [
										-0.375,
										0.375
									]
								},
								"west": {
									"uv": [
										5.375,
										1.875
									],
									"uv_size": [
										-0.125,
										0.375
									]
								},
								"up": {
									"uv": [
										7.25,
										7.625
									],
									"uv_size": [
										-0.375,
										0.125
									]
								},
								"down": {
									"uv": [
										8,
										7
									],
									"uv_size": [
										-0.375,
										-0.125
									]
								}
							},
							"inflate": -0.25
						}
					],
					"parent": "head_up",
					"rotation": [
						2.35667,
						17.34552,
						-54.64047
					]
				},
				{
					"name": "head_down",
					"pivot": [
						-0.0484,
						25.77346,
						-8.56152
					],
					"cubes": [
						{
							"origin": [
								-2.94543,
								25.04356,
								-13.1141
							],
							"size": [
								5.79406,
								2.27132,
								6.27806
							],
							"uv": {
								"north": {
									"uv": [
										7.125,
										0.75
									],
									"uv_size": [
										0.875,
										0.25
									]
								},
								"east": {
									"uv": [
										7.125,
										2.125
									],
									"uv_size": [
										0.875,
										0.25
									]
								},
								"south": {
									"uv": [
										2.25,
										7.125
									],
									"uv_size": [
										0.875,
										0.25
									]
								},
								"west": {
									"uv": [
										7.125,
										2.375
									],
									"uv_size": [
										0.875,
										0.25
									]
								},
								"up": {
									"uv": [
										1.75,
										3.5
									],
									"uv_size": [
										0.875,
										0.875
									]
								},
								"down": {
									"uv": [
										3.5,
										2.75
									],
									"uv_size": [
										0.875,
										-0.875
									]
								}
							},
							"inflate": 0
						}
					],
					"parent": "head2",
					"rotation": [
						17.5,
						0,
						0
					]
				},
				{
					"name": "bone19",
					"pivot": [
						0,
						26.15502,
						-12.48315
					],
					"cubes": [
						{
							"origin": [
								-1.96794,
								26.30196,
								-16.64381
							],
							"size": [
								3.93589,
								1.01292,
								3.52972
							],
							"uv": {
								"north": {
									"uv": [
										7.375,
										9
									],
									"uv_size": [
										0.625,
										0.125
									]
								},
								"east": {
									"uv": [
										6.5,
										8.875
									],
									"uv_size": [
										0.375,
										0.125
									]
								},
								"south": {
									"uv": [
										10.25,
										6.125
									],
									"uv_size": [
										0.625,
										0.25
									]
								},
								"west": {
									"uv": [
										6.5,
										8.5
									],
									"uv_size": [
										0.375,
										0.125
									]
								},
								"up": {
									"uv": [
										10,
										7
									],
									"uv_size": [
										0.625,
										0.375
									]
								},
								"down": {
									"uv": [
										9.875,
										5.375
									],
									"uv_size": [
										0.625,
										-0.375
									]
								}
							},
							"inflate": 0
						},
						{
							"origin": [
								-2.06474,
								25.04356,
								-16.74061
							],
							"size": [
								4.12949,
								1.30332,
								3.62652
							],
							"uv": {
								"north": {
									"uv": [
										7.125,
										2.625
									],
									"uv_size": [
										0.625,
										0.25
									]
								},
								"east": {
									"uv": [
										7.625,
										3.375
									],
									"uv_size": [
										0.375,
										0.25
									]
								},
								"south": {
									"uv": [
										4.75,
										7.125
									],
									"uv_size": [
										0.625,
										0.25
									]
								},
								"west": {
									"uv": [
										7.625,
										3.625
									],
									"uv_size": [
										0.375,
										0.25
									]
								},
								"up": {
									"uv": [
										7,
										6.5
									],
									"uv_size": [
										0.625,
										0.375
									]
								},
								"down": {
									"uv": [
										7,
										7.25
									],
									"uv_size": [
										0.625,
										-0.375
									]
								}
							},
							"inflate": 0
						}
					],
					"parent": "head_down"
				},
				{
					"name": "bone13",
					"pivot": [
						-0.08,
						28.19892,
						-1.64702
					],
					"cubes": [
						{
							"origin": [
								-1.92,
								27.68465,
								-4.59275
							],
							"size": [
								3.68,
								0.88,
								2.16
							],
							"pivot": [
								0,
								30.4243,
								-2.34163
							],
							"rotation": [
								17.5,
								0,
								0
							],
							"uv": {
								"north": {
									"uv": [
										5.5,
										1.75
									],
									"uv_size": [
										2,
										0.5
									]
								},
								"east": {
									"uv": [
										4.5,
										1.75
									],
									"uv_size": [
										1,
										0.5
									]
								},
								"south": {
									"uv": [
										6.75,
										5
									],
									"uv_size": [
										1,
										1
									]
								},
								"west": {
									"uv": [
										5.5,
										1.75
									],
									"uv_size": [
										-1,
										0.5
									]
								},
								"up": {
									"uv": [
										2.5,
										0.5
									],
									"uv_size": [
										-2,
										0.75
									]
								},
								"down": {
									"uv": [
										2.5,
										1.25
									],
									"uv_size": [
										-2,
										-0.75
									]
								}
							},
							"inflate": 0
						}
					],
					"parent": "head",
					"rotation": [
						-17.5,
						0,
						0
					]
				},
				{
					"name": "bone14",
					"pivot": [
						-0.08,
						29.45557,
						-1.67521
					],
					"cubes": [
						{
							"origin": [
								-1.92,
								28.63129,
								-4.21617
							],
							"size": [
								3.68,
								1.28,
								2.16
							],
							"pivot": [
								0,
								30.49094,
								-1.96506
							],
							"rotation": [
								17.5,
								0,
								0
							],
							"uv": {
								"north": {
									"uv": [
										5.5,
										1.25
									],
									"uv_size": [
										2,
										0.75
									]
								},
								"east": {
									"uv": [
										4.5,
										1.25
									],
									"uv_size": [
										1,
										0.75
									]
								},
								"south": {
									"uv": [
										0.5,
										0.5
									],
									"uv_size": [
										2,
										0.75
									]
								},
								"west": {
									"uv": [
										5.5,
										1.25
									],
									"uv_size": [
										-1,
										0.75
									]
								},
								"up": {
									"uv": [
										2.5,
										0.5
									],
									"uv_size": [
										-2,
										0.75
									]
								},
								"down": {
									"uv": [
										2.5,
										1.25
									],
									"uv_size": [
										-2,
										-0.75
									]
								}
							},
							"inflate": 0
						}
					],
					"parent": "head",
					"rotation": [
						-17.5,
						0,
						0
					]
				}
			]
		}
	]
}