{
	"format_version": "1.8.0",
	"animations": {
		"animation.zorra.geo.CAM1Cphase1": {
			"loop": true,
			"bones": {
				"upperpart": {
					"rotation": [0, 0, 10]
				},
				"feddyHed": {
					"rotation": [0, 0, 2.5]
				},
				"head": {
					"rotation": [0, 0, -12.5]
				},
				"eyebrows": {
					"position": [0, -0.5, 0]
				},
				"jaw": {
					"rotation": [27.5, 0, 0]
				},
				"eyepatch": {
					"rotation": [-107.5, 0, 0]
				},
				"eyelid": {
					"rotation": [-17.5, 0, 0]
				},
				"eyelid2": {
					"rotation": [-7.5, 0, 0]
				},
				"armL": {
					"rotation": [0, -35, 17.5]
				},
				"lower": {
					"rotation": [-20, 0, 0]
				},
				"hook": {
					"rotation": [-26.43596, 58.95768, -30.12627]
				},
				"armR": {
					"rotation": [0, 37.5, -25]
				},
				"lower2": {
					"rotation": [-27.5, 0, 0]
				},
				"hand2": {
					"rotation": [0, 25, 0]
				},
				"foot": {
					"rotation": [0, -5, 0]
				},
				"legR": {
					"rotation": [0, 0, -5],
					"position": [0.25, 0, 0]
				},
				"foot2": {
					"rotation": [-1.5741, -17.43127, 5.24133],
					"position": [0, -0.25, 0]
				}
			}
		},
		"animation.zorra.geo.CAM1Aphase2": {
			"loop": true,
			"bones": {
				"upperpart": {
					"rotation": [-7.5, 0, 0]
				},
				"head": {
					"rotation": [-7.5, 10, 70],
					"position": [1, 3, 0]
				},
				"jaw": {
					"rotation": [32.5, 0, 0]
				},
				"eyepatch": {
					"rotation": [-127.5, 0, 0]
				},
				"eyelid": {
					"rotation": [-10, 0, 0]
				},
				"eyelid2": {
					"rotation": [-7.5, 0, 0]
				},
				"armL": {
					"rotation": [-32.5, 0, 10]
				},
				"lower": {
					"rotation": [-110.44582, 11.73507, -4.3361]
				},
				"hook": {
					"rotation": [-25.50555, 67.73126, -27.27317]
				},
				"armR": {
					"rotation": [14.87739, 1.93597, -29.74721]
				},
				"lower2": {
					"rotation": [-34.3569, 7.13136, 10.29284]
				},
				"hand2": {
					"rotation": [-50.51436, 61.77771, -54.02155]
				},
				"fingers3": {
					"rotation": [0, 0, -30]
				}
			}
		},
		"animation.zorra.geo.kazotskykick": {
			"loop": true,
			"animation_length": 1.5,
			"bones": {
				"feddy": {
					"position": {
						"0.0": [0, -7, 0],
						"0.4167": [0, -3.25, 0],
						"0.7917": [0, -7, 0],
						"1.2083": [0, -3.25, 0],
						"1.5": [0, -7, 0]
					}
				},
				"upperpart": {
					"rotation": {
						"0.0": [4.66733, -7.71069, 2.51322],
						"0.4167": [5, 0, 0],
						"0.7917": [4.66733, 7.71069, -2.51322],
						"1.0833": [5, 0, 0],
						"1.5": [4.66733, -7.71069, 2.51322]
					},
					"position": {
						"0.0": [0, 0, 0],
						"0.2917": [0, -1, 0],
						"0.5": [0, 1, 0],
						"0.7917": [0, 0, 0],
						"1.0": [0, -1, 0],
						"1.2917": [0, 1, 0],
						"1.5": [0, 0, 0]
					}
				},
				"head": {
					"rotation": {
						"0.0": [-4.6673, 7.71069, -2.51322],
						"0.4167": [-4.6673, 0, 0],
						"0.7917": [-4.6673, -7.71069, 2.51322],
						"1.0833": [-4.6673, 0, 0],
						"1.5": [-4.6673, 7.71069, -2.51322]
					},
					"position": {
						"0.0": [0, 0, 0],
						"0.2083": [0, 1, 0],
						"0.5": [0, -1, 0],
						"0.7917": [0, 0, 0],
						"1.0": [0, 1, 0],
						"1.2917": [0, -1, 0],
						"1.5": [0, 0, 0]
					}
				},
				"jaw": {
					"rotation": {
						"0.0": [0, 0, 0],
						"0.2083": [5, 0, 0],
						"0.5": [-7.5, 0, 0],
						"0.7917": [0, 0, 0],
						"1.0": [5, 0, 0],
						"1.2917": [-7.5, 0, 0],
						"1.5": [0, 0, 0]
					}
				},
				"eyepatch": {
					"rotation": {
						"0.0": [0, 0, 0],
						"0.2083": [5, 0, 0],
						"0.5": [-30, 0, 0],
						"0.7917": [0, 0, 0],
						"1.0": [5, 0, 0],
						"1.2917": [-30, 0, 0],
						"1.5": [0, 0, 0]
					}
				},
				"earL": {
					"rotation": {
						"0.0": [0, 0, 0],
						"0.2083": [0, 0, -10],
						"0.5": [0, 0, 10],
						"0.7917": [0, 0, 0],
						"1.0": [0, 0, -10],
						"1.2917": [0, 0, 10],
						"1.5": [0, 0, 0]
					}
				},
				"earL2": {
					"rotation": {
						"0.0": [0, 0, 0],
						"0.2083": [0, 0, 10],
						"0.5": [0, 0, -10],
						"0.7917": [0, 0, 0],
						"1.0": [0, 0, 10],
						"1.2917": [0, 0, -10],
						"1.5": [0, 0, 0]
					}
				},
				"eyelid": {
					"rotation": [-10, 0, 0]
				},
				"eyelid2": {
					"rotation": [-10, 0, 0]
				},
				"armL": {
					"rotation": {
						"0.0": [-27.59298, -6.73717, 62.06341],
						"0.4167": [-7.63538, -5.52433, 26.14146],
						"0.7917": [10, 0, 20],
						"1.0833": [-7.63538, -5.52433, 26.14146],
						"1.5": [-27.59298, -6.73717, 62.06341]
					}
				},
				"lower": {
					"rotation": {
						"0.0": [-122.5, 0, 0],
						"0.4167": [-89.5, 0, 0],
						"0.7917": [-22.5, 0, 0],
						"1.0833": [-32.5, 0, 0],
						"1.5": [-122.5, 0, 0]
					}
				},
				"hook": {
					"rotation": {
						"0.0": [-10, 0, 0],
						"0.5": [-40, 0, 0],
						"0.7917": [-10, 0, 0],
						"1.2083": [22.5, 0, 0],
						"1.5": [-10, 0, 0]
					}
				},
				"armR": {
					"rotation": {
						"0.0": [10, 0, -20],
						"0.4167": [-7.63538, 5.52433, -26.14146],
						"0.7917": [-27.59298, 6.73717, -62.06341],
						"1.0833": [-7.63538, 5.52433, -26.14146],
						"1.5": [10, 0, -20]
					}
				},
				"lower2": {
					"rotation": {
						"0.0": [-22.5, 0, 0],
						"0.2917": [-32.5, 0, 0],
						"0.7917": [-122.5, 0, 0],
						"1.0833": [-89.5, 0, 0],
						"1.5": [-22.5, 0, 0]
					}
				},
				"hand2": {
					"rotation": {
						"0.0": [-10, 0, 0],
						"0.5": [22.5, 0, 0],
						"0.7917": [-10, 0, 0],
						"1.2083": [-40, 0, 0],
						"1.5": [-10, 0, 0]
					}
				},
				"thumb3": {
					"rotation": [40, 0, 0]
				},
				"belowpart": {
					"rotation": {
						"0.0": [0, 0, -7.5],
						"0.4167": [0, 0, 0],
						"0.7917": [0, 0, 7.5],
						"1.0833": [0, 0, 0],
						"1.5": [0, 0, -7.5]
					}
				},
				"pelvissuit": {
					"rotation": {
						"0.0": [-15.98448, 7.43547, -7.56397],
						"0.4167": [-15.98, 0, 0],
						"0.7917": [-15.98448, -7.43547, 7.56397],
						"1.0833": [-15.98, 0, 0],
						"1.5": [-15.98448, 7.43547, -7.56397]
					}
				},
				"legL": {
					"rotation": {
						"0.0": [-39.51073, 36.35521, 21.41092],
						"0.7917": [-87.4388, 40.02585, -20.84189],
						"1.5": [-39.51073, 36.35521, 21.41092]
					},
					"position": {
						"0.0": [0, 0, 0],
						"0.7917": [-1, 1, -1],
						"1.5": [0, 0, 0]
					}
				},
				"lower3": {
					"rotation": {
						"0.0": [137.5, 0, 0],
						"0.4167": [68.5, 0, 0],
						"0.7917": [-7.5, 0, 0],
						"1.0833": [0, 0, 0],
						"1.5": [137.5, 0, 0]
					}
				},
				"foot": {
					"rotation": {
						"0.0": [-72.24687, -9.53274, -3.03513],
						"0.4167": [-15.83512, -7.55211, 4.28027],
						"0.7917": [-7.5, 0, 0],
						"1.2083": [-25, 0, 0],
						"1.5": [-72.24687, -9.53274, -3.03513]
					}
				},
				"legR": {
					"rotation": {
						"0.0": [-87.4388, -40.02585, 20.84189],
						"0.7917": [-39.51073, -36.35521, -21.41092],
						"1.5": [-87.4388, -40.02585, 20.84189]
					},
					"position": {
						"0.0": [1, 1, -1],
						"0.7917": [0, 0, 0],
						"1.5": [1, 1, -1]
					}
				},
				"lower4": {
					"rotation": {
						"0.0": [-7.5, 0, 0],
						"0.2917": [0, 0, 0],
						"0.7917": [137.5, 0, 0],
						"1.2083": [68.5, 0, 0],
						"1.5": [-7.5, 0, 0]
					}
				},
				"foot2": {
					"rotation": {
						"0.0": [-7.5, 0, 0],
						"0.5": [-25, 0, 0],
						"0.7917": [-72.24687, 9.53274, 3.03513],
						"1.0833": [-15.83512, 7.55211, -4.28027],
						"1.5": [-7.5, 0, 0]
					}
				}
			}
		}
	}
}